[
  {
    "id": "cut-zum-001",
    "provider": "ZumRails",
    "key": "rotate_api_key",
    "label": "Rotate Zum Rails API key",
    "description": "Issue a new key in the Zum portal, deploy to PaySpyre, then revoke the TurnKey-held key.",
    "status": "PENDING",
    "completed_by": null,
    "completed_at": null,
    "notes": null,
    "created_at": "2026-05-10T00:00:00.000Z",
    "updated_at": "2026-05-10T00:00:00.000Z"
  },
  {
    "id": "cut-zum-002",
    "provider": "ZumRails",
    "key": "rotate_webhook_secret",
    "label": "Rotate Zum webhook signing secret",
    "description": "Generate a fresh HMAC secret, update PaySpyre verification, retire the TurnKey one.",
    "status": "PENDING",
    "completed_by": null,
    "completed_at": null,
    "notes": null,
    "created_at": "2026-05-10T00:00:00.000Z",
    "updated_at": "2026-05-10T00:00:00.000Z"
  },
  {
    "id": "cut-zum-003",
    "provider": "ZumRails",
    "key": "switch_webhook_pad_returns",
    "label": "Switch PAD return / NSF webhook → PaySpyre",
    "description": "Point bounce notifications at /api/webhooks/zum/pad-returns. Required before PaySpyre processes any debits.",
    "status": "PENDING",
    "completed_by": null,
    "completed_at": null,
    "notes": null,
    "created_at": "2026-05-10T00:00:00.000Z",
    "updated_at": "2026-05-10T00:00:00.000Z"
  },
  {
    "id": "cut-zum-004",
    "provider": "ZumRails",
    "key": "switch_webhook_payment_status",
    "label": "Switch payment status webhook → PaySpyre",
    "description": "Posted / failed / cancelled callbacks to /api/webhooks/zum/payments.",
    "status": "PENDING",
    "completed_by": null,
    "completed_at": null,
    "notes": null,
    "created_at": "2026-05-10T00:00:00.000Z",
    "updated_at": "2026-05-10T00:00:00.000Z"
  },
  {
    "id": "cut-zum-005",
    "provider": "ZumRails",
    "key": "ip_allowlist",
    "label": "Add PaySpyre platform IPs to Zum allowlist",
    "description": "Vercel egress IPs + any future fixed-IP proxy.",
    "status": "PENDING",
    "completed_by": null,
    "completed_at": null,
    "notes": null,
    "created_at": "2026-05-10T00:00:00.000Z",
    "updated_at": "2026-05-10T00:00:00.000Z"
  },
  {
    "id": "cut-zum-006",
    "provider": "ZumRails",
    "key": "pad_form_template",
    "label": "Re-verify PAD-007 form template",
    "description": "PaySpyre branding + lender info on the borrower-facing PAD form.",
    "status": "PENDING",
    "completed_by": null,
    "completed_at": null,
    "notes": null,
    "created_at": "2026-05-10T00:00:00.000Z",
    "updated_at": "2026-05-10T00:00:00.000Z"
  },
  {
    "id": "cut-flinks-001",
    "provider": "Flinks",
    "key": "rotate_api_key",
    "label": "Rotate Flinks API key",
    "description": "Issue PaySpyre-owned key, deploy, revoke the TurnKey-held key.",
    "status": "PENDING",
    "completed_by": null,
    "completed_at": null,
    "notes": null,
    "created_at": "2026-05-10T00:00:00.000Z",
    "updated_at": "2026-05-10T00:00:00.000Z"
  },
  {
    "id": "cut-flinks-002",
    "provider": "Flinks",
    "key": "switch_webhook_verification",
    "label": "Switch verification-complete webhook → PaySpyre",
    "description": "Bank-verification completion callbacks to /api/webhooks/flinks/verification.",
    "status": "PENDING",
    "completed_by": null,
    "completed_at": null,
    "notes": null,
    "created_at": "2026-05-10T00:00:00.000Z",
    "updated_at": "2026-05-10T00:00:00.000Z"
  },
  {
    "id": "cut-flinks-003",
    "provider": "Flinks",
    "key": "redirect_url",
    "label": "Update post-login redirect URL",
    "description": "Borrower returns to PaySpyre Originations after Flinks login flow.",
    "status": "PENDING",
    "completed_by": null,
    "completed_at": null,
    "notes": null,
    "created_at": "2026-05-10T00:00:00.000Z",
    "updated_at": "2026-05-10T00:00:00.000Z"
  },
  {
    "id": "cut-flinks-004",
    "provider": "Flinks",
    "key": "subscription_tier",
    "label": "Confirm Flinks Capital subscription tier",
    "description": "PaySpyre needs the Capital tier for the income/balance signals on the Bank tab.",
    "status": "PENDING",
    "completed_by": null,
    "completed_at": null,
    "notes": null,
    "created_at": "2026-05-10T00:00:00.000Z",
    "updated_at": "2026-05-10T00:00:00.000Z"
  },
  {
    "id": "cut-signnow-001",
    "provider": "SignNow",
    "key": "rotate_api_key",
    "label": "Rotate SignNow API key",
    "description": "Issue PaySpyre key, deploy, revoke TurnKey one.",
    "status": "PENDING",
    "completed_by": null,
    "completed_at": null,
    "notes": null,
    "created_at": "2026-05-10T00:00:00.000Z",
    "updated_at": "2026-05-10T00:00:00.000Z"
  },
  {
    "id": "cut-signnow-002",
    "provider": "SignNow",
    "key": "switch_webhook_signature",
    "label": "Switch signature-complete webhook → PaySpyre",
    "description": "/api/webhooks/signnow/complete; required before any new agreement can fully execute.",
    "status": "PENDING",
    "completed_by": null,
    "completed_at": null,
    "notes": null,
    "created_at": "2026-05-10T00:00:00.000Z",
    "updated_at": "2026-05-10T00:00:00.000Z"
  },
  {
    "id": "cut-signnow-003",
    "provider": "SignNow",
    "key": "template_ids",
    "label": "Re-verify document template ids",
    "description": "Loan agreement / disclosure templates referenced by PaySpyre on send.",
    "status": "PENDING",
    "completed_by": null,
    "completed_at": null,
    "notes": null,
    "created_at": "2026-05-10T00:00:00.000Z",
    "updated_at": "2026-05-10T00:00:00.000Z"
  },
  {
    "id": "cut-sendgrid-001",
    "provider": "SendGrid",
    "key": "rotate_api_key",
    "label": "Rotate SendGrid API key",
    "description": "Issue PaySpyre-owned key, deploy, revoke TurnKey one.",
    "status": "PENDING",
    "completed_by": null,
    "completed_at": null,
    "notes": null,
    "created_at": "2026-05-10T00:00:00.000Z",
    "updated_at": "2026-05-10T00:00:00.000Z"
  },
  {
    "id": "cut-sendgrid-002",
    "provider": "SendGrid",
    "key": "switch_webhook_events",
    "label": "Switch event webhook → PaySpyre",
    "description": "Bounce / unsubscribe / spam-report events to /api/webhooks/sendgrid/events.",
    "status": "PENDING",
    "completed_by": null,
    "completed_at": null,
    "notes": null,
    "created_at": "2026-05-10T00:00:00.000Z",
    "updated_at": "2026-05-10T00:00:00.000Z"
  },
  {
    "id": "cut-sendgrid-003",
    "provider": "SendGrid",
    "key": "template_ids",
    "label": "Migrate template IDs to PaySpyre namespace",
    "description": "Re-create transactional email templates under PaySpyre account; update PaySpyre code to reference the new ids.",
    "status": "PENDING",
    "completed_by": null,
    "completed_at": null,
    "notes": null,
    "created_at": "2026-05-10T00:00:00.000Z",
    "updated_at": "2026-05-10T00:00:00.000Z"
  },
  {
    "id": "cut-sendgrid-004",
    "provider": "SendGrid",
    "key": "spf_dkim",
    "label": "Update SPF / DKIM records",
    "description": "DNS at PaySpyre's domain registrar must authorize the PaySpyre-owned SendGrid sender.",
    "status": "PENDING",
    "completed_by": null,
    "completed_at": null,
    "notes": null,
    "created_at": "2026-05-10T00:00:00.000Z",
    "updated_at": "2026-05-10T00:00:00.000Z"
  },
  {
    "id": "cut-equifax-001",
    "provider": "Equifax",
    "key": "rotate_api_key",
    "label": "Rotate Equifax API credentials",
    "description": "PaySpyre-owned member number + secret. Confirm bureau team has the new lender details on file.",
    "status": "PENDING",
    "completed_by": null,
    "completed_at": null,
    "notes": null,
    "created_at": "2026-05-10T00:00:00.000Z",
    "updated_at": "2026-05-10T00:00:00.000Z"
  },
  {
    "id": "cut-equifax-002",
    "provider": "Equifax",
    "key": "switch_callback_url",
    "label": "Switch hard-pull callback URL → PaySpyre",
    "description": "Bureau result delivery to /api/webhooks/equifax/result.",
    "status": "PENDING",
    "completed_by": null,
    "completed_at": null,
    "notes": null,
    "created_at": "2026-05-10T00:00:00.000Z",
    "updated_at": "2026-05-10T00:00:00.000Z"
  },
  {
    "id": "cut-equifax-003",
    "provider": "Equifax",
    "key": "verify_member",
    "label": "Re-verify member / account number",
    "description": "PaySpyre as the named lender on every credit pull receipt + adverse-action notice.",
    "status": "PENDING",
    "completed_by": null,
    "completed_at": null,
    "notes": null,
    "created_at": "2026-05-10T00:00:00.000Z",
    "updated_at": "2026-05-10T00:00:00.000Z"
  },
  {
    "id": "cut-walnut-001",
    "provider": "Walnut",
    "key": "rotate_api_key",
    "label": "Rotate Walnut API key (if integrated)",
    "description": "Only required once creditor-insurance enrollment goes live; safe to leave PENDING until then.",
    "status": "PENDING",
    "completed_by": null,
    "completed_at": null,
    "notes": null,
    "created_at": "2026-05-10T00:00:00.000Z",
    "updated_at": "2026-05-10T00:00:00.000Z"
  },
  {
    "id": "cut-msgbird-001",
    "provider": "MessageBird",
    "key": "rotate_api_key",
    "label": "Rotate MessageBird API key",
    "description": "MessageBird is currently inactive; mark this item N/A until SMS goes live.",
    "status": "N/A",
    "completed_by": null,
    "completed_at": null,
    "notes": "SMS not active in production. Re-open when MessageBird is wired up.",
    "created_at": "2026-05-10T00:00:00.000Z",
    "updated_at": "2026-05-10T00:00:00.000Z"
  }
]
